someip/__init__.py
someip/config.py
someip/header.py
someip/sd.py
someip/service.py
someip/utils.py
someip-0.3.0.dist-info/LICENSE.txt
someip-0.3.0.dist-info/METADATA
someip-0.3.0.dist-info/WHEEL
someip-0.3.0.dist-info/top_level.txt
someip-0.3.0.dist-info/zip-safe
someip-0.3.0.dist-info/RECORD
