Metadata-Version: 2.1
Name: someip
Version: 0.3.0
Home-page: https://github.com/afflux/pysomeip
Author: Kjell Braden
Author-email: afflux@pentabarf.de
License: MIT
Project-URL: Documentation, https://pysomeip.readthedocs.io/en/latest/
Project-URL: Source, https://github.com/afflux/pysomeip
Classifier: Intended Audience :: Developers
Classifier: License :: OSI Approved :: MIT License
Classifier: Development Status :: 4 - Beta
Classifier: Operating System :: MacOS :: MacOS X
Classifier: Operating System :: POSIX
Classifier: Operating System :: POSIX :: BSD
Classifier: Operating System :: POSIX :: Linux
Classifier: Operating System :: Microsoft :: Windows
Classifier: Programming Language :: Python
Classifier: Programming Language :: Python :: 3.8
Requires-Python: >=3.8
License-File: LICENSE.txt
Provides-Extra: docs
Requires-Dist: sphinx (>=3.0.1) ; extra == 'docs'
